AUTHORS
CHANGES
INSTALL.rst
LICENSE
MANIFEST.in
README.rst
REQUIRED
setup.cfg
setup.py
setup_utils.py
acrilog/__init__.py
acrilog.egg-info/PKG-INFO
acrilog.egg-info/SOURCES.txt
acrilog.egg-info/dependency_links.txt
acrilog.egg-info/requires.txt
acrilog.egg-info/top_level.txt
acrilog/bin/__init__.py
acrilog/bin/sshlogger_socket_handler.py
acrilog/lib/__init__.py
acrilog/lib/baselogger.py
acrilog/lib/mplogger.py
acrilog/lib/sshlogger_pipe_handler.py
acrilog/lib/sshlogger_socket_handler.py
acrilog/lib/sshlogger_socket_server.py
acrilog/lib/utils.py