Metadata-Version: 1.1
Name: acrilog
Version: 2.0.13
Summary: acrilog is a Python library of providing multiprocessing idiomto us in multiprocessing environment
Home-page: https://github.com/Acrisel/acrilog
Author: Acrisel Team
Author-email: support@acrisel.com
License: MIT
Keywords: library logger multiprocessing
Platform: UNKNOWN
Classifier: Development Status :: 5 - Production/Stable
Classifier: Environment :: Other Environment
Classifier: Intended Audience :: Developers
Classifier: License :: OSI Approved :: MIT License
Classifier: Operating System :: OS Independent
Classifier: Programming Language :: Python
Classifier: Programming Language :: Python :: 3
Classifier: Programming Language :: Python :: 3.2
Classifier: Programming Language :: Python :: 3.3
Classifier: Programming Language :: Python :: 3.4
Classifier: Programming Language :: Python :: 3.5
Classifier: Topic :: Software Development :: Libraries :: Application Frameworks
Classifier: Topic :: Software Development :: Libraries :: Python Modules
